geodetector/__init__.py
geodetector/gd_regressor.py
geodetector/geodetector.py
geodetector/dataset/__init__.py
geodetector/dataset/_load_data.py
geodetector/dataset/data/disease.csv
geodetector/utils/__init__.py
geodetector/utils/_groupby.py
geodetector-0.0.5.dist-info/METADATA
geodetector-0.0.5.dist-info/WHEEL
geodetector-0.0.5.dist-info/licenses/LICENSE
geodetector-0.0.5.dist-info/RECORD
