Metadata-Version: 2.1
Name: geodetector
Version: 0.0.5
Summary: a tool for detect the relationship between variables
Project-URL: Homepage, https://github.com/lvyaqiao/geodetector
Project-URL: Bug Tracker, https://github.com/lvyaqiao/geodetector/issues
Author-email: lvyaqiao <lvyaqiao@126.com>
License-File: LICENSE
Classifier: License :: OSI Approved :: MIT License
Classifier: Operating System :: OS Independent
Classifier: Programming Language :: Python :: 3
Requires-Python: >=3.7
Requires-Dist: numpy>=1.17
Requires-Dist: pandas>=0.25
Requires-Dist: scikit-learn>=0.21
Requires-Dist: seaborn>=0.9
